Metadata-Version: 2.1
Name: google-datacatalog-teradata-connector
Version: 0.9.0
Summary: Library for ingesting Teradata metadata into Google Cloud Data Catalog
Home-page: UNKNOWN
Author: Google LLC
License: UNKNOWN
Platform: Posix; MacOS X; Windows
Classifier: Development Status :: 4 - Beta
Classifier: Programming Language :: Python :: 3.7
Requires-Dist: teradatasql
Requires-Dist: google-datacatalog-rdbms-connector (>=0.12.0<0.13.0)
